st_zoom_buttons/__init__.py
st_zoom_buttons/example.py
st_zoom_buttons/frontend/build/asset-manifest.json
st_zoom_buttons/frontend/build/bootstrap.min.css
st_zoom_buttons/frontend/build/bootstrap.min.css.map
st_zoom_buttons/frontend/build/index.html
st_zoom_buttons/frontend/build/static/js/main.b0a4d4f9.js
st_zoom_buttons/frontend/build/static/js/main.b0a4d4f9.js.LICENSE.txt
st_zoom_buttons/frontend/build/static/js/main.b0a4d4f9.js.map
st_zoom_buttons-0.0.1.dist-info/licenses/LICENSE
st_zoom_buttons-0.0.1.dist-info/METADATA
st_zoom_buttons-0.0.1.dist-info/WHEEL
st_zoom_buttons-0.0.1.dist-info/top_level.txt
st_zoom_buttons-0.0.1.dist-info/RECORD
